horreum/__init__.py
horreum/configs.py
horreum/horreum_client.py
horreum/keycloak_access_provider.py
horreum/raw_client/.kiota.log
horreum/raw_client/api/api_request_builder.py
horreum/raw_client/api/config/config_request_builder.py
horreum/raw_client/api/config/datastore/datastore_request_builder.py
horreum/raw_client/api/config/datastore/item/datastore_item_request_builder.py
horreum/raw_client/api/config/datastore/item/test/test_request_builder.py
horreum/raw_client/api/config/datastore/types/types_request_builder.py
horreum/raw_client/api/config/keycloak/keycloak_request_builder.py
horreum/raw_client/api/config/version/version_request_builder.py
horreum/raw_client/api/dataset/dataset_request_builder.py
horreum/raw_client/api/dataset/item/dataset_item_request_builder.py
horreum/raw_client/api/dataset/item/label_values/label_values_request_builder.py
horreum/raw_client/api/dataset/item/preview_label/preview_label_request_builder.py
horreum/raw_client/api/dataset/item/summary/summary_request_builder.py
horreum/raw_client/api/dataset/list_/by_run/by_run_request_builder.py
horreum/raw_client/api/dataset/list_/by_run/item/with_run_item_request_builder.py
horreum/raw_client/api/dataset/list_/by_schema/by_schema_request_builder.py
horreum/raw_client/api/dataset/list_/by_test/by_test_request_builder.py
horreum/raw_client/api/dataset/list_/by_test/item/with_test_item_request_builder.py
horreum/raw_client/api/dataset/list_/list_request_builder.py
horreum/raw_client/api/experiment/experiment_request_builder.py
horreum/raw_client/api/experiment/item/profiles/item/with_profile_item_request_builder.py
horreum/raw_client/api/experiment/item/profiles/profiles_request_builder.py
horreum/raw_client/api/experiment/item/with_test_item_request_builder.py
horreum/raw_client/api/experiment/models_requests/models_request_builder.py
horreum/raw_client/api/experiment/run/run_request_builder.py
horreum/raw_client/api/run/autocomplete/autocomplete_request_builder.py
horreum-0.19.dist-info/LICENSE
horreum-0.19.dist-info/METADATA
horreum-0.19.dist-info/WHEEL
horreum-0.19.dist-info/RECORD
