Metadata-Version: 2.1
Name: horreum
Version: 0.19
Summary: Horreum python library
Home-page: https://github.com/Hyperfoil/horreum-client-python
License: Apache 2.0
Keywords: horreum,performance,change-detection
Author: Andrea Lamparelli
Author-email: alampare@redhat.com
Maintainer: Andrea Lamparelli
Maintainer-email: alampare@redhat.com
Requires-Python: >=3.9,<4.0
Classifier: License :: Other/Proprietary License
Classifier: Programming Language :: Python :: 3
Classifier: Programming Language :: Python :: 3.9
Classifier: Programming Language :: Python :: 3.10
Classifier: Programming Language :: Python :: 3.11
Classifier: Programming Language :: Python :: 3.12
Requires-Dist: microsoft-kiota-abstractions (>=1.7.1,<2.0.0)
Requires-Dist: microsoft-kiota-http (>=1.7.1,<2.0.0)
Requires-Dist: microsoft-kiota-serialization-form (>=1.7.0,<2.0.0)
Requires-Dist: microsoft-kiota-serialization-json (>=1.7.0,<2.0.0)
Requires-Dist: microsoft-kiota-serialization-multipart (>=1.7.0,<2.0.0)
Requires-Dist: microsoft-kiota-serialization-text (>=1.7.0,<2.0.0)
Requires-Dist: python-keycloak (>=3.9.1,<4.0.0)
Project-URL: Issues, https://github.com/Hyperfoil/horreum-client-python/issues
